felstorm_nexus_utils/__init__.py
felstorm_nexus_utils/form.py
felstorm_nexus_utils/flask/__init__.py
felstorm_nexus_utils/flask/blueprints.py
felstorm_nexus_utils/flask/utils.py
felstorm_nexus_utils-0.0.14.dist-info/LICENSE
felstorm_nexus_utils-0.0.14.dist-info/METADATA
felstorm_nexus_utils-0.0.14.dist-info/WHEEL
felstorm_nexus_utils-0.0.14.dist-info/top_level.txt
felstorm_nexus_utils-0.0.14.dist-info/RECORD
