Metadata-Version: 2.1
Name: felstorm-nexus-utils
Version: 0.0.14
Summary: Utility functions for Felstorm Nexus projects
Home-page: https://github.com/pypa/felstorm-nexus-utils
Author: Felstorm
Author-email: support@felstorm.com
License: UNKNOWN
Project-URL: Bug Tracker, https://github.com/pypa/felstorm-nexus-utils/issues
Platform: UNKNOWN
Classifier: Programming Language :: Python :: 3
Classifier: License :: OSI Approved :: MIT License
Classifier: Operating System :: OS Independent
Requires-Python: >=3.6
Requires-Dist: flask
Requires-Dist: jinja2
